tuinty_forpy_eight/2048.md
tuinty_forpy_eight/2048.tcss
tuinty_forpy_eight/__init__.py
tuinty_forpy_eight/main.py
tuinty_forpy_eight-1.3.1.dist-info/METADATA
tuinty_forpy_eight-1.3.1.dist-info/WHEEL
tuinty_forpy_eight-1.3.1.dist-info/entry_points.txt
tuinty_forpy_eight-1.3.1.dist-info/top_level.txt
tuinty_forpy_eight-1.3.1.dist-info/RECORD
