Metadata-Version: 2.1
Name: tuinty-forpy-eight
Version: 1.3.1
Summary: A tui implementation of the game "2048", made with textual
Home-page: https://github.com/TotalyEnglizLitrate/tuinty-forpy-eight
Author: TotalyEnglizLitrate
Requires-Dist: textual >=0.39.0
